yeoda/__init__.py
yeoda/datacube.py
yeoda/errors.py
yeoda/utils.py
yeoda-1.0.0.dist-info/AUTHORS.rst
yeoda-1.0.0.dist-info/LICENSE.txt
yeoda-1.0.0.dist-info/METADATA
yeoda-1.0.0.dist-info/WHEEL
yeoda-1.0.0.dist-info/top_level.txt
yeoda-1.0.0.dist-info/RECORD
