Metadata-Version: 2.1
Name: yeoda
Version: 1.0.0
Summary: yeoda provides datacube classes for reading and writing well-defined and structured earth observation data
Home-page: https://github.com/TUW-GEO/yeoda
Author: TU Wien RS group
Author-email: remote.sensing@geo.tuwien.ac.at
License: MIT
Download-URL: https://github.com/TUW-GEO/yeoda/archive/v0.3.0.tar.gz
Keywords: Earth Observation,Remote Sensing,Data Reader,Data Writer,Data Cube
Platform: any
Classifier: Development Status :: 4 - Beta
Classifier: License :: OSI Approved :: MIT License
Classifier: Topic :: Scientific/Engineering
Classifier: Topic :: Software Development :: Version Control :: Git
Classifier: Programming Language :: Python :: 3.8
Classifier: Natural Language :: English
Requires-Dist: veranda
Requires-Dist: geopathfinder
Provides-Extra: testing
Requires-Dist: pytest-cov ; extra == 'testing'
Requires-Dist: coverage ; extra == 'testing'
Requires-Dist: pytest ; extra == 'testing'
